hello/__init__.py
hello/app.py
actions_pipeline_example-0.2.0.dist-info/METADATA
actions_pipeline_example-0.2.0.dist-info/WHEEL
actions_pipeline_example-0.2.0.dist-info/entry_points.txt
actions_pipeline_example-0.2.0.dist-info/top_level.txt
actions_pipeline_example-0.2.0.dist-info/RECORD
