Metadata-Version: 2.1
Name: actions-pipeline-example
Version: 0.2.0
Summary: Dummy project to test GitHub actions
Home-page: https://github.com/cognitedata/actions-pipeline-example
Author: Carlos
Author-email: carlos.pereira@cognite.com
License: UNKNOWN
Platform: UNKNOWN
